kubi_ecs_logger/__init__.py
kubi_ecs_logger/utils.py
kubi_ecs_logger/models/__init__.py
kubi_ecs_logger/models/base.py
kubi_ecs_logger/models/include.py
kubi_ecs_logger/models/root_schema.py
kubi_ecs_logger/models/severity.py
kubi_ecs_logger/models/fields/__init__.py
kubi_ecs_logger/models/fields/agent.py
kubi_ecs_logger/models/fields/client.py
kubi_ecs_logger/models/fields/cloud.py
kubi_ecs_logger/models/fields/container.py
kubi_ecs_logger/models/fields/destination.py
kubi_ecs_logger/models/fields/ecs.py
kubi_ecs_logger/models/fields/error.py
kubi_ecs_logger/models/fields/event.py
kubi_ecs_logger/models/fields/field_set.py
kubi_ecs_logger/models/fields/file.py
kubi_ecs_logger/models/fields/geo.py
kubi_ecs_logger/models/fields/group.py
kubi_ecs_logger/models/fields/host.py
kubi_ecs_logger/models/fields/http.py
kubi_ecs_logger/models/fields/logline.py
kubi_ecs_logger/models/fields/network.py
kubi_ecs_logger/models/fields/observer.py
kubi_ecs_logger/models/fields/organization.py
kubi_ecs_logger/models/fields/os.py
kubi_ecs_logger/models/fields/process.py
kubi_ecs_logger/models/fields/related.py
kubi_ecs_logger/models/fields/server.py
kubi_ecs_logger/models/fields/service.py
kubi_ecs_logger/models/fields/source.py
kubi_ecs_logger/models/fields/url.py
kubi_ecs_logger/models/fields/user.py
kubi_ecs_logger/models/fields/useragent.py
kubi_ecs_logger/wrapper/__init__.py
kubi_ecs_logger/wrapper/logger.py
kubi_ecs_logger-0.1.3.dist-info/licenses/LICENSE
kubi_ecs_logger-0.1.3.dist-info/METADATA
kubi_ecs_logger-0.1.3.dist-info/WHEEL
kubi_ecs_logger-0.1.3.dist-info/top_level.txt
kubi_ecs_logger-0.1.3.dist-info/RECORD
