Metadata-Version: 2.4
Name: kubi_ecs_logger
Version: 0.1.3
Summary: Logger based on Elasticsearch Common Schema.
Author: Kumina
Author-email: bartv@kumina.nl
License: BSD-3-Clause
Project-URL: Kumina, https://kumina.nl/index
Project-URL: Source, https://github.com/kumina/kubi_ecs_logger
Keywords: logging elasticsearch esc
Classifier: Development Status :: 3 - Alpha
Classifier: Intended Audience :: Developers
Classifier: Topic :: System :: Logging
Classifier: Programming Language :: Python :: 3.6
Classifier: Programming Language :: Python :: 3.7
Requires-Python: >=3.6, <4
License-File: LICENSE
Requires-Dist: marshmallow~=3.26.2
Dynamic: author
Dynamic: author-email
Dynamic: classifier
Dynamic: description
Dynamic: description-content-type
Dynamic: keywords
Dynamic: license
Dynamic: license-file
Dynamic: project-url
Dynamic: requires-dist
Dynamic: requires-python
Dynamic: summary
